Workbook

Sheet Prospect Pipeline
A1: Company Name | B1: Industry | C1: HQ City | D1: Nearest Campus | E1: Giving Channel | F1: Focus Areas | G1: Contact Name | H1: Contact Title | I1: Contact Email | J1: Contact LinkedIn | K1: Alignment (1-5) | L1: Proximity (1-5) | M1: Capacity (1-5) | N1: Total Score | O1: Pipeline Stage | P1: Last Action | Q1: Last Action Date | R1: Next Step | S1: Next Step Date | T1: Ask Amount | U1: Amount Received | V1: Notes
A2: Apple Inc. | B2: Technology | C2: Cupertino | D2: De Anza College | E2: Corporate Foundation | F2: Education, Community, Environment | H2: Community Affairs | K2: 5 | L2: 5 | M2: 5 | N2: =IF(AND(K2<>"",L2<>"",M2<>""),K2+L2+M2,"") -> 15 | O2: 1-Research | R2: Research Apple Community Grant Program | V2: Apple has strong community giving in Cupertino area
A3: Google / Alphabet | B3: Technology | C3: Mountain View | D3: Foothill College | E3: Corporate Foundation | F3: Education, Food Security, Racial Equity | H3: Google.org Program Manager | K3: 5 | L3: 4 | M3: 5 | N3: =IF(AND(K3<>"",L3<>"",M3<>""),K3+L3+M3,"") -> 14 | O3: 1-Research | R3: Check Google.org grant cycles | V3: Google.org Impact Challenge may be relevant
A4: Intuit | B4: Technology | C4: Mountain View | D4: Foothill College | E4: Corporate Foundation | F4: Financial Empowerment, Education, Food Security | H4: Community Investment Manager | K4: 5 | L4: 4 | M4: 4 | N4: =IF(AND(K4<>"",L4<>"",M4<>""),K4+L4+M4,"") -> 13 | O4: 1-Research | R4: Review Intuit Foundation focus areas | V4: Intuit has strong Bay Area community focus
A5: Cisco Systems | B5: Technology | C5: San Jose | D5: De Anza College | E5: Corporate Foundation | F5: Education, Basic Needs, Community | H5: Cisco Foundation Director | K5: 4 | L5: 4 | M5: 5 | N5: =IF(AND(K5<>"",L5<>"",M5<>""),K5+L5+M5,"") -> 13 | O5: 1-Research | R5: Research Cisco Foundation grants | V5: Cisco Foundation very active in Silicon Valley
A6: Salesforce | B6: Technology | C6: San Francisco | D6: All Campuses | E6: Multiple | F6: Education, Workforce Development, Community | H6: Community Impact Manager | K6: 4 | L6: 3 | M6: 5 | N6: =IF(AND(K6<>"",L6<>"",M6<>""),K6+L6+M6,"") -> 12 | O6: 1-Research | R6: Check Salesforce community grants | V6: 1-1-1 model: 1% equity, time, product to community
A7: Kaiser Permanente | B7: Healthcare | C7: Oakland | D7: Chabot College | E7: Corporate Foundation | F7: Health, Food Security, Community Health | H7: Community Benefit Manager | K7: 5 | L7: 5 | M7: 5 | N7: =IF(AND(K7<>"",L7<>"",M7<>""),K7+L7+M7,"") -> 15 | O7: 1-Research | R7: Review KP Community Benefit grants | V7: KP has specific food security/nutrition grants
A8: Wells Fargo | B8: Financial Services | C8: San Francisco | D8: All Campuses | E8: Corporate Foundation | F8: Education, Community Development, Housing | H8: Regional Foundation Officer | K8: 4 | L8: 3 | M8: 5 | N8: =IF(AND(K8<>"",L8<>"",M8<>""),K8+L8+M8,"") -> 12 | O8: 1-Research | R8: Check Wells Fargo Foundation open grants | V8: Large foundation with regional community focus
A9: Applied Materials | B9: Technology | C9: Santa Clara | D9: De Anza College | E9: Corporate Foundation | F9: Education, Community, STEM | H9: Community Affairs | K9: 3 | L9: 5 | M9: 4 | N9: =IF(AND(K9<>"",L9<>"",M9<>""),K9+L9+M9,"") -> 12 | O9: 1-Research | R9: Research Applied Materials Foundation | V9: HQ very close to De Anza campus
A10: Palo Alto Networks | B10: Technology | C10: Santa Clara | D10: Foothill College | E10: CSR Budget | F10: Community, Education | H10: CSR Manager | K10: 3 | L10: 4 | M10: 3 | N10: =IF(AND(K10<>"",L10<>"",M10<>""),K10+L10+M10,"") -> 10 | O10: 1-Research | R10: Research community giving program | V10: Growing company with community programs
A11: Clorox Company | B11: Consumer Goods | C11: Oakland | D11: Chabot College | E11: Corporate Foundation | F11: Community Health, Education | H11: Foundation Program Officer | K11: 3 | L11: 5 | M11: 4 | N11: =IF(AND(K11<>"",L11<>"",M11<>""),K11+L11+M11,"") -> 12 | O11: 1-Research | R11: Review Clorox Foundation grants | V11: Strong Oakland/East Bay community ties
N12: =IF(AND(K12<>"",L12<>"",M12<>""),K12+L12+M12,"")
N13: =IF(AND(K13<>"",L13<>"",M13<>""),K13+L13+M13,"")
N14: =IF(AND(K14<>"",L14<>"",M14<>""),K14+L14+M14,"")
N15: =IF(AND(K15<>"",L15<>"",M15<>""),K15+L15+M15,"")
N16: =IF(AND(K16<>"",L16<>"",M16<>""),K16+L16+M16,"")
N17: =IF(AND(K17<>"",L17<>"",M17<>""),K17+L17+M17,"")
N18: =IF(AND(K18<>"",L18<>"",M18<>""),K18+L18+M18,"")
N19: =IF(AND(K19<>"",L19<>"",M19<>""),K19+L19+M19,"")
N20: =IF(AND(K20<>"",L20<>"",M20<>""),K20+L20+M20,"")
N21: =IF(AND(K21<>"",L21<>"",M21<>""),K21+L21+M21,"")
N22: =IF(AND(K22<>"",L22<>"",M22<>""),K22+L22+M22,"")
N23: =IF(AND(K23<>"",L23<>"",M23<>""),K23+L23+M23,"")
... N51: =IF(AND(K51<>"",L51<>"",M51<>""),K51+L51+M51,"")

Sheet Grant Deadlines
A1: Company / Foundation | B1: Grant Program Name | C1: Focus Area | D1: Application Opens | E1: Deadline | F1: Typical Award Range | G1: Application URL | H1: Status | I1: Notes

Sheet Dashboard
A1: CORPORATE FUNDRAISING DASHBOARD
A3: Pipeline Summary | D3: Stage Breakdown
A4: Total Prospects | B4: =COUNTA('Prospect Pipeline'!A2:A51) -> 10 | D4: 1-Research | E4: =COUNTIF('Prospect Pipeline'!O2:O51,"1-Research") -> 10
A5: In Active Outreach | B5: =COUNTIFS('Prospect Pipeline'!O2:O51,"3-Outreach Sent")+COUNTIFS('Prospect Pipeline'!O2:O51,"4-Meeting Scheduled")+COUNTIFS('Prospect Pipeline'!O2:O51,"5-Meeting Complete") -> 0 | D5: 2-Contact Identified | E5: =COUNTIF('Prospect Pipeline'!O2:O51,"2-Contact Identified") -> 0
A6: Proposals Submitted | B6: =COUNTIF('Prospect Pipeline'!O2:O51,"6-Proposal Submitted")+COUNTIF('Prospect Pipeline'!O2:O51,"7-Decision Pending") -> 0 | D6: 3-Outreach Sent | E6: =COUNTIF('Prospect Pipeline'!O2:O51,"3-Outreach Sent") -> 0
A7: Funded | B7: =COUNTIF('Prospect Pipeline'!O2:O51,"8-Funded!") -> 0 | D7: 4-Meeting Scheduled | E7: =COUNTIF('Prospect Pipeline'!O2:O51,"4-Meeting Scheduled") -> 0
A8: Total Ask Amount | B8: =SUMPRODUCT(('Prospect Pipeline'!T2:T51<>"")*'Prospect Pipeline'!T2:T51) -> 0 | D8: 5-Meeting Complete | E8: =COUNTIF('Prospect Pipeline'!O2:O51,"5-Meeting Complete") -> 0
A9: Total Received | B9: =SUMPRODUCT(('Prospect Pipeline'!U2:U51<>"")*'Prospect Pipeline'!U2:U51) -> 0 | D9: 6-Proposal Submitted | E9: =COUNTIF('Prospect Pipeline'!O2:O51,"6-Proposal Submitted") -> 0
D10: 7-Decision Pending | E10: =COUNTIF('Prospect Pipeline'!O2:O51,"7-Decision Pending") -> 0
D11: 8-Funded! | E11: =COUNTIF('Prospect Pipeline'!O2:O51,"8-Funded!") -> 0
D12: 9-Declined | E12: =COUNTIF('Prospect Pipeline'!O2:O51,"9-Declined") -> 0
A15: Instructions:
A16: 1. Add prospects in the 'Prospect Pipeline' tab
A17: 2. Track grant deadlines in the 'Grant Deadlines' tab
A18: 3. Update Pipeline Stages as you progress with each prospect
A19: 4. This dashboard auto-updates from your pipeline data
